print_pretty/__init__.py
print_pretty/cli.py
print_pretty/pprint_custom.py
print_pretty/print_pretty.py
print_pretty-0.1.1.dist-info/entry_points.txt
print_pretty-0.1.1.dist-info/WHEEL
print_pretty-0.1.1.dist-info/METADATA
print_pretty-0.1.1.dist-info/RECORD
