Metadata-Version: 2.1
Name: print-pretty
Version: 0.1.1
Summary: 
Home-page: https://github.com/eyalev/print-pretty
Author: Eyal Levin
Author-email: eyalev@gmail.com
Requires-Python: >=3.6,<4.0
Classifier: Programming Language :: Python :: 3
Classifier: Programming Language :: Python :: 3.6
Classifier: Programming Language :: Python :: 3.7
Classifier: Programming Language :: Python :: 3.8
Requires-Dist: click (>=7.1.2,<8.0.0)
Requires-Dist: input-util (>=0.1.2,<0.2.0)
Requires-Dist: print-dict (>=0.1.3,<0.2.0)
Requires-Dist: pyyaml (>=5.3.1,<6.0.0)
Requires-Dist: yapf (>=0.30.0,<0.31.0)
Project-URL: Repository, https://github.com/eyalev/print-pretty
